{
    "SMLTME.12hr": "12小時",
    "SMLTME.24hr": "24小時",
    "SMLTME.Large_Step": "大步進量",
    "SMLTME.Large_Step_Hint": "使用<<和>>按鈕增減分鐘的數值。按住Shift雙倍增減。",
    "SMLTME.Resting_Opacity": "待機透明度",
    "SMLTME.Resting_Opacity_Hint": "未與SmallTime窗口進行互動時的窗口透明度。",
    "SMLTME.Darkness_Default": "默認影響黑暗等級",
    "SMLTME.Darkness_Default_Hint": "在場景設置中將SmallTime黑暗等級控制設為默認。",
    "SMLTME.AboutTime": "與About Time同步",
    "SMLTME.Hide_From_Players": "對玩家隱藏",
    "SMLTME.Hide_From_Players_Hint": "對所有非GM用戶隱藏SmallTIme窗口。",
    "SMLTME.Allow_Trusted": "允許Trusted用戶組玩家控制",
    "SMLTME.Darkness_Control_Hint": "將場景的黑暗等級與SmallTIme當前時間進行關聯。",
    "SMLTME.Player_Visibility": "玩家可見性",
    "SMLTME.Player_Visibility_Hint": "選擇場景中的玩家可以看見 SmallTime 的哪些部分。默認選項已設置在在模組設置中。",
    "SMLTME.Player_Visibility_Default": "默認玩家可見度",
    "SMLTME.Player_Vis_0": "無",
    "SMLTME.Player_Vis_1": "僅日/月位置",
    "SMLTME.Player_Vis_2": "日/月位置和時間",
    "SMLTME.Darkness_Reset": "按住Shift點擊將時間重置為默認",
    "SMLTME.Time_Format": "時間格式",
    "SMLTME.Small_Step": "小步進量",
    "SMLTME.Small_Step_Hint": "使用<和>按鈕增減分鐘的數值。按住Shift雙倍增減。",
    "SMLTME.Darkness_Control": "黑暗等級控制",
    "SMLTME.Darkness_Config": "黑暗等級配置",
    "SMLTME.Darkness_Config_Hint": "拖動太陽和月亮以設置日出日落時間。它們的高度確定了黑暗等級的最大/最小值。",
    "SMLTME.AboutTime_Hint": "如果About Time時鐘改變了，SmallTime也會一起改變，反之亦然。將SmallTime時間加過午夜也會改變About Time日期。",
    "SMLTME.Allow_Trusted_Hint": "Trusted用戶組的玩家可以改變當前時間。",
    "SMLTME.Player_Visibility_Default_Hint": "場景的默認可見等級。",
    "SMLTME.Player_Vis_3": "使用默認設置",
    "SMLTME.Date_Format": "日期格式",
    "SMLTME.Calendar_Provider_Hint": "你的世界的日歷信息的來源。",
    "SMLTME.Calendar_Provider": "日歷提供方",
    "SMLTME.Position_Reset": "按住 Shift 點擊以重置 SmallTime 窗口位置",
    "SMLTME.Sun_Sync": "同步日出/日落",
    "SMLTME.Sun_Sync_Hint": "需要Simple Calendar中的日出和日落時間。",
    "SMLTME.Show_Seconds": "顯示秒",
    "SMLTME.Threshold_Override_Tooltip": "SmallTime 正根據月相調整該項",
    "SMLTME.Moonlight_Adjust": "月光調整",
    "SMLTME.Moonlight_Adjust_Hint": "根據當前月相調整全局光照閾值。",
    "SMLTME.Moon_Darkness_Hint": "基于當前月相自適應最大黑暗等級。",
    "SMLTME.Moon_Darkness": "月相影響黑暗等級"
}
