{
  "I18N": {
    "LANGUAGE": "English",
    "MAINTAINERS": "gambit"
  },
  "CONTROLS": {
    "Effects": "FXMaster Controls",
    "ParticleEffects": "Particle Effects",
    "InvertMask": "Invert Particle Effect Mask",
    "Filters": "Filter Effects",
    "SaveMacro": "Save Particle and Filter Effects as Macro",
    "ClearFX": "Clear Scene Particle and Filter Effects",
    "ToolsActive": "FXMaster Tools"
  },
  "FXMASTER": {
    "Common": {
      "ParticleEffect": "Particle Effect",
      "FilterEffect": "Filter Effect",
      "ParticleEffectsManagementTitle": "Particle Effects Management",
      "FilterEffectsManagementTitle": "Filter Effects Management",
      "SaveChanges": "Save Changes",
      "EnableEffects": "Enable Effects",
      "DisableAll": "Disable Effects For Everybody",
      "DisableAllHint": "Setting this will disable effects for all users. It overrides the enable flag. It's mostly a safe guard to deactivate effects when migrations fail. You shouldn't need to set this yourself. After changing this setting, a manual reload is required.",
      "ClearParticleAndFilterEffectsTitle": "Clear Particle and Filter Effects",
      "ClearParticleAndFilterEffectsContent": "<p>Permanently delete all <em>Particle Effects</em> and <em>Filter Effects</em> from this Scene?</p>",
      "ResetPassiveParameters": "Reset Particle and Filter Parameters",
      "ResetPassiveParametersHint": "Resets Particle and Filter parameters to their default values",
      "ResetPassiveSuccess": "Particle and Filter parameters successfully reset",
      "Yes": "Yes",
      "No": "No",
      "Enable": "Enable",
      "ErrorCannotFindEffect": "FXMaster | Couldn't find effect data.",
      "Environment": "Environment",
      "Interface": "Interface",
      "Music": "Music",
      "EnableTooltips": "Enable Tooltips",
      "EnableTooltipsHint": "Enables tooltip descriptions for Particle and Filter effect parameters.",
      "HideEffects": "Hide Effects",
      "HideParticleEffectsTitle": "Hide Particle Effects",
      "HideFilterEffectsTitle": "Hide Filter Effects",
      "HiddenEffectsHint": "Toggle effects to hide them from this management list (per-user). Hidden effects can still be enabled via the API.",
      "ActiveEffectTooltip": "Currently active",
      "HideEffectsTooltip": "Hidden effects: {count}",
      "ApiEffects": "Manage API Effects",
      "ApiEffectsManagementTitle": "Manage API Effects",
      "ApiEffectsKind": "Kind",
      "ApiEffectsName": "Name",
      "ApiEffectsType": "Type",
      "ApiEffectsActions": "Actions",
      "ApiEffectsDelete": "Delete",
      "ApiEffectsDetails": "API Parameters",
      "ApiEffectsNone": "No API effects are active on this Scene.",
      "ApiEffectsKindParticle": "Particle",
      "ApiEffectsKindFilter": "Filter",
      "ApiEffectsEdit": "Edit",
      "ApiEffectsEditUnavailable": "Edit (unavailable)",
      "ApiEffectEditorTitle": "Edit API Effect",
      "ApiEffectMissing": "This API effect no longer exists on this Scene.",
      "Unknown": "Unknown"
    },
    "Params": {
      "Saturation": "Saturation",
      "Gamma": "Gamma",
      "Brightness": "Brightness",
      "Contrast": "Contrast",
      "Tint": "Tint",
      "Opacity": "Opacity",
      "Scale": "Scale",
      "ScaleHint": "Video scaling",
      "Blur": "Blur",
      "Bloom": "Bloom",
      "Sepia": "Sepia",
      "Threshold": "Threshold",
      "Period": "Period",
      "Duration": "Duration",
      "Speed": "Speed",
      "Lifetime": "Lifetime",
      "Density": "Density",
      "Direction": "Direction",
      "LineWidth": "Line Width",
      "Animations": "Animations",
      "Variants": "Variants",
      "Variant": {
        "Cute": "Cute",
        "Creepy": "Creepy"
      },
      "Anchor": "Anchor",
      "AnchorHint": "Local coordinates of the origin between 0.0 and 1.0",
      "Spin": "Spin Speed",
      "Noise": "Noise Density",
      "ScratchSize": "Scratch Size",
      "ScratchDensity": "Scratch Density",
      "NoiseSize": "Noise Size",
      "Wobble": "Wobble",
      "WobbleFrequency": "Wobble Frequency",
      "Displacement": "Displacement",
      "Streakiness": "Streakiness",
      "Lift": "Lift",
      "Glow": "Glow",
      "Parallel": "Parallel Rays",
      "Angle": "Emission Point/Angle",
      "Gain": "Ray Intensity",
      "Lacunarity": "Ray Volume",
      "BeamLength": "Ray Length",
      "FadePercent": "Edge Fade %",
      "Rainbow": "Rainbow",
      "Shadow": "Shadow",
      "ShadowRotation": "Shadow Position",
      "ShadowDistance": "Shadow Distance",
      "ShadowBlur": "Shadow Blur",
      "ShadowOpacity": "Shadow Opacity",
      "BelowTokens": "Below Tokens",
      "ShadowOnly": "Shadow Only",
      "Splash": "Splash",
      "Orbit": "Orbit",
      "OrbitDistance": "Orbit Distance",
      "FillMode": "Fill Mode",
      "Slices": "Slices",
      "Offset": "Offset",
      "RedX": "Red X",
      "RedY": "Red Y",
      "GreenX": "Green X",
      "GreenY": "Green Y",
      "BlueX": "Blue X",
      "BlueY": "Blue Y",
      "Seed": "Seed",
      "RefreshRate": "Refresh Rate",
      "SliceEnable": "Enable Slices",
      "SliceCrosshatch": "Slice Crosshatch",
      "SliceCount": "Slice Count",
      "SliceSpeed": "Slice Speed",
      "SliceBurstRate": "Slice Randomization",
      "SliceOffset": "Slice Offset",
      "SliceDirection": "Slice Direction",
      "SlicePixelation": "Slice Pixelation",
      "SliceShardAngle": "Slice Shard Angle",
      "SliceRedX": "Slice Red X",
      "SliceRedY": "Slice Red Y",
      "SliceGreenX": "Slice Green X",
      "SliceGreenY": "Slice Green Y",
      "SliceBlueX": "Slice Blue X",
      "SliceBlueY": "Slice Blue Y",
      "MatrixGlyphs": "Enable Glyphs",
      "GlyphDirection": "Glyph Direction",
      "GlyphColor": "Glyph Tint",
      "GlyphIntensity": "Glyph Intensity",
      "GlyphCellSize": "Glyph Cell Size",
      "GlyphMoveSpeed": "Glyph Move Speed",
      "GlyphDensity": "Glyph Density",
      "GlyphSlicePct": "Glyph Slice %",
      "GlyphFlickerSpeed": "Glyph Flicker Speed",
      "FishType": {
        "Name": "Fish Type",
        "Koi": "Koi",
        "KoiSpirit": "Koi Spirit",
        "KoiPainted": "Koi Painted",
        "Betta": "Betta",
        "MantaRay": "Manta Ray",
        "MantaRaySpirit": "Manta Ray Spirit",
        "MantaRayPainted": "Manta Ray Painted",
        "BettaRainbow": "Betta Rainbow",
        "BettaBluePink": "Betta Blue/Pink",
        "BettaPurple": "Betta Purple",
        "BettaGreen": "Betta Green",
        "BettaRed": "Betta Red",
        "BettaRedYellow": "Betta Red/Yellow"
      },
      "FishAnimations": {
        "Glide": "Glide",
        "Swim": "Swim",
        "Mixed": "Mixed"
      },
      "RotationStrength": "Rotation Strength",
      "Trail": "Trail",
      "LateralMovement": "Lateral Movement",
      "SoundFxEnabled": "Sound FX",
      "ThunderAware": "Thunder Aware",
      "ThunderChannels": "Thunder Channels",
      "ThunderBassThreshold": "Thunder Bass Threshold",
      "TopDown": "Top Down",
      "Jitter": "Jitter",
      "DirectionalMovement": "Directional Movement",
      "Spread": "Directional Spread",
      "LightningMode": "Lightning Mode",
      "LightningModeHorizontal": "Horizontal",
      "LightningModeMixed": "Mixed",
      "BoltFrequency": "Bolt Frequency",
      "BoltLength": "Bolt Length",
      "Branchiness": "Branchiness",
      "SyncFlash": "Sync with Lightning Flash",
      "TopDownScale": "Top Down Scale",
      "TopDownBolts": "Top Down Bolts",
      "TopDownBoltsVariable": "Variable Bolt Count",
      "TriggerChance": "Trigger Chance",
      "FrostStrength": "Frost Strength",
      "Depth": "Depth",
      "VeinStrength": "Vein Strength",
      "SheenStrength": "Sheen Strength",
      "SheenTint": "Sheen Tint",
      "ReflectionStrength": "Reflection Strength",
      "ReflectionDistance": "Reflection Distance",
      "ReflectionBlur": "Reflection Blur",
      "ReflectionFresnel": "Reflection Fresnel",
      "WaterTint": "Water Tint",
      "WaterStrength": "Water Strength",
      "WaterSpeed": "Water Speed",
      "Caustics": "Caustics",
      "CausticStrength": "Caustic Strength",
      "CausticsTint": "Caustics Tint",
      "Refraction": "Refraction",
      "Reflection": "Reflection",
      "Sparkle": "Sparkle",
      "FlowingWater": "Flowing Water",
      "FollowRegionPath": "Follow Region Path",
      "PathInfluence": "Path Influence",
      "Waves": "Waves",
      "WaveStrength": "Wave Strength",
      "Turbulence": "Turbulence",
      "FlowSpeed": "Flow Speed",
      "FlowDirection": "Flow Direction",
      "FlowStrength": "Flow Strength",
      "StillWaterSpeed": "Still Water Speed",
      "WaveSpeed": "Wave Speed",
      "WaveDirection": "Wave Direction",
      "VortexWater": "Vortex Water",
      "VortexSpeed": "Vortex Speed",
      "VortexDirection": "Vortex Direction",
      "VortexStrength": "Vortex Strength",
      "VortexClockwise": "Clockwise Rotation",
      "BelowTiles": "Below Tiles",
      "DarknessActivationRange": "Darkness Activation Range",
      "DarknessActivationMinimum": "Darkness Minimum",
      "DarknessActivationMaximum": "Darkness Maximum",
      "BelowForeground": "Below Foreground",
      "DarknessActivationMin": "Darkness Activation Min",
      "DarknessActivationMax": "Darkness Activation Max",
      "BlendMode": "Blend Mode",
      "Levels": "Levels",
      "AllLevels": "All Levels",
      "DarknessActivationEnabled": "Darkness Activation"
    },
    "ParamTooltips": {
      "Saturation": "Color intensity. 0 = grayscale; 1 = original; >1 = oversaturated.",
      "Gamma": "Midtone curve. Lower brightens midtones; higher darkens midtones.",
      "Brightness": "Overall scene or sprite brightness. 0 = black; 1 = original; >1 = brighter.",
      "Contrast": "Difference between light and dark. Higher values increase punch.",
      "Tint": "Apply a solid color tint. Toggle Apply to enable the tint color.",
      "Opacity": "Global transparency of the effect. 0 = invisible; 1 = fully opaque.",
      "Scale": "Animation/particle scaling. Higher = larger particles.",
      "Blur": "Blur radius or strength applied by the effect.",
      "Bloom": "Bloom intensity—how strongly bright areas glow.",
      "Sepia": "Sepia toning amount. Higher = stronger vintage look.",
      "Threshold": "Brightness threshold; lower catches more pixels.",
      "Period": "Cycle period for repeating animation, in milliseconds. Lower = faster cycles.",
      "Duration": "How long an effect or transition runs (fade or playback), in seconds.",
      "Speed": "Motion/animation speed. Higher = faster movement or change.",
      "Lifetime": "Average life of particles and related frequency. Higher = longer-lived.",
      "Density": "How many particles spawn per area. Higher = busier effect. NOTE: Higher densities will have a greater impact on performance.",
      "Direction": "Orientation in degrees for emission or motion.",
      "LineWidth": "Width of lines/scanlines in pixels (effect-specific).",
      "Animations": "Select animation types for this effect.",
      "Variants": "Choose a preset look for this effect.",
      "Variant": {
        "Cute": "Cloth-like cute variant.",
        "Creepy": "Spookier humanoid variant."
      },
      "Anchor": "Local coordinates of the origin between 0.0 and 1.0.",
      "Spin": "Spin/rotation speed of elements. Higher = faster spin.",
      "Noise": "Strength of film grain / noise. Higher = more visible grain.",
      "ScratchSize": "Average size/thickness of scratches.",
      "ScratchDensity": "How many scratches appear.",
      "NoiseSize": "Grain size scale. Higher = larger individual grains.",
      "Wobble": "Adds random side to side particle movement. Higher = more movement.",
      "WobbleFrequency": "Controls how fast particles wobble. Higher = faster wobble.",
      "Displacement": "Strength of warping on particle effect.",
      "Streakiness": "Controls how stretched and banded the filter is along the movement path. Lower values look more like uniform haze, higher values create longer streaks.",
      "Lift": "Controls how thick the filter is in the middle of each sheet compared to its edges. Lower values are more flat and even; higher values make the centers denser and the edges thinner, adding depth but reducing overall coverage.",
      "Glow": "Glow intensity around particle sprites",
      "Parallel": "Use parallel rays instead of radial.",
      "Angle": "Emission point/angle in degrees.",
      "Gain": "Intensity multiplier.",
      "Lacunarity": "Spacing factor for fractal rays. Higher = denser detail.",
      "BeamLength": "Maximum visible length of beams/rays.",
      "FadePercent": "Softens region edges by this percent for a smoother blend. Higher = more fade.",
      "Rainbow": "Overrides Tint and enables a random cycling rainbow effect on particles.",
      "Shadow": "Enable a drop shadow for the particle sprites.",
      "ShadowRotation": "Shadow angle in degrees.",
      "ShadowDistance": "Offset distance of the drop shadow. Higher = further away.",
      "ShadowBlur": "Blur strength on the drop shadow.",
      "ShadowOpacity": "Opacity of the drop shadow. 0 = invisible; 1 = fully opaque.",
      "BelowTokens": "Renders effects underneath tokens visually.",
      "ShadowOnly": "Render only the drop shadow and hide the base particle sprites.",
      "Splash": "Enable rain splash effects alongside raindrops.",
      "Orbit": "Enables orbit around center of a container instead of an outward spread.",
      "OrbitDistance": "Distance from the center of a container for orbiting particles.",
      "FillMode": "Controls how the glitch effect fills the affected area.",
      "Slices": "Controls the overall slice layer amount for glitch distortion.",
      "Offset": "Maximum displacement amount applied by the glitch effect.",
      "RedX": "Red channel horizontal offset.",
      "RedY": "Red channel vertical offset.",
      "GreenX": "Green channel horizontal offset.",
      "GreenY": "Green channel vertical offset.",
      "BlueX": "Blue channel horizontal offset.",
      "BlueY": "Blue channel vertical offset.",
      "Seed": "Random seed used to vary the generated pattern.",
      "RefreshRate": "How often the generated pattern re-randomizes.",
      "SliceEnable": "Enables slice displacement and RGB split.",
      "SliceCrosshatch": "Adds a second slice band pattern at a different phase for a crosshatch look.",
      "SliceCount": "Number of horizontal slices. Higher = more fragmented slices.",
      "SliceSpeed": "How fast the slice pattern scrolls. 0 disables slice scrolling.",
      "SliceBurstRate": "How often slice sizes/offsets re-randomize, in seconds. 0 disables randomization.",
      "SliceOffset": "Maximum displacement amount for each slice.",
      "SliceDirection": "Direction (degrees) that slices displace.",
      "SlicePixelation": "Adds blocky pixel stepping to slices. 0 = smooth.",
      "SliceShardAngle": "Adds angular shard-like shearing to slices. 0 = none.",
      "SliceRedX": "Red channel X offset (chromatic split).",
      "SliceRedY": "Red channel Y offset (chromatic split).",
      "SliceGreenX": "Green channel X offset (chromatic split).",
      "SliceGreenY": "Green channel Y offset (chromatic split).",
      "SliceBlueX": "Blue channel X offset (chromatic split).",
      "SliceBlueY": "Blue channel Y offset (chromatic split).",
      "MatrixGlyphs": "Overlay Glyph pattern.",
      "GlyphDirection": "Direction (degrees) the Glyph field is oriented.",
      "MatrixDirection": "Direction (degrees) the Glyph field is oriented.",
      "GlyphColor": "Tint color for glyphs. Toggle Apply off to use the rainbow mode instead.",
      "GlyphIntensity": "Brightness of the glyph overlay. 0 disables glyph visibility.",
      "GlyphCellSize": "Size of each glyph cell in pixels.",
      "GlyphMoveSpeed": "Speed of Glyph motion simulation. 0 disables movement.",
      "GlyphDensity": "How many glyph columns are active. 0 = none; 1 = all columns.",
      "GlyphSlicePct": "If slices are enabled, how much of the slice region gets glyphs.",
      "GlyphFlickerSpeed": "How fast glyphs blink. 0 disables flicker.",
      "FishType": {
        "Name": "Choose which fish variant to spawn."
      },
      "RotationStrength": "How strongly particles rotate as they move. Higher = more rotation.",
      "Trail": "Trail intensity/length behind particle sprites. Higher = longer/stronger trails.",
      "LateralMovement": "Adds smooth side-to-side drifting to particle movement. Higher = more lateral drift.",
      "SoundFxEnabled": "Enable Sound FX rule matching for this effect.",
      "ThunderAware": "React to audio peaks. NOTE: This is meant for Thunder, but will apply to any bass effect in audio so choose Channel accordingly.",
      "ThunderChannels": "Which audio channels to react to.",
      "ThunderBassThreshold": "Bass level required to trigger thunder reactions. Higher = less sensitive.",
      "TopDown": "Play effect in top-down mode",
      "Jitter": "How jagged the bolt path is. Higher values create more chaotic arcs and branching.",
      "DirectionalMovement": "Play effect in specific direction",
      "Spread": "Determine spread offset from direction in degrees",
      "LightningMode": "Choose how bolts are generated: Horizontal streaks, Top Down strikes, or a mix of both.",
      "BoltFrequency": "How often a bolt spawns on average. Higher values produce more frequent bolts.",
      "BoltLength": "Controls the overall bolt length. In Top Down mode this sets the foreshortened strike depth.",
      "Branchiness": "Controls how strongly the bolt branches and how many sub-branches it can form.",
      "SyncFlash": "When enabled, Lightning Bolts will trigger flashes from the base Lightning filter and suppress its autonomous flashing so flashes occur only when bolts spawn.",
      "TopDownScale": "Scales the size of Top Down strikes (beam and origin flash). Does not affect Horizontal bolts.",
      "TopDownBolts": "Maximum number of simultaneous Top Down strikes. In Variable Bolt Count mode, this is the maximum possible bolts per strike event.",
      "TopDownBoltsVariable": "If enabled, chooses a random number of Top Down bolts up to the maximum (biased toward lower counts). If disabled, always spawns exactly the maximum number.",
      "TriggerChance": "In Audio Aware mode, this controls how often audio triggers spawn a bolt. When Sync with Lightning Flash is enabled, this controls how often each flash also spawns a bolt.",
      "FrostStrength": "Controls how strongly the ice veil (frost) tints the scene. Higher = more frosty/opaque ice look.",
      "Depth": "Controls how much the under-ice layer contributes (movement/caustics). Higher = more visible depth beneath the ice.",
      "VeinStrength": "Darkens and adds subtle vein-like structure within the ice. 0 disables the veins.",
      "SheenStrength": "Strength of the ice sheen highlight layer. Higher = brighter sheen.",
      "SheenTint": "Tint color for the sheen highlight layer.",
      "ReflectionStrength": "Strength of the reflection-like sampling for glossy ice. Higher = stronger reflection.",
      "ReflectionDistance": "How far the reflection is sampled/offset. Higher = more pronounced reflection shift.",
      "ReflectionBlur": "Blur applied to the reflection sample. Higher = softer reflection.",
      "ReflectionFresnel": "Controls how view-angle dependent the reflection is. Higher = tighter, more edge-weighted reflection.",
      "WaterTint": "Tint color applied to the water layer or surface coloration.",
      "WaterStrength": "Strength of the animated under-ice water refraction and tint. Higher = more visible movement.",
      "WaterSpeed": "Speed of the under-ice water motion. Higher = faster movement.",
      "Caustics": "Controls how sparse or widespread the sun-caustic filaments are. Lower = very fine, very sparse light lines; higher = broader, more frequent caustic coverage.",
      "CausticStrength": "How strongly the caustic lighting brightens the water surface. Higher = brighter, more obvious light-caustic streaks.",
      "CausticsTint": "Tint color applied to the caustic light contribution.",
      "Refraction": "Strength of the water distortion/refraction. Higher = more visible scene warping beneath the surface.",
      "Reflection": "Strength of glossy sunlight and scene reflection on the water. Higher = more visible reflective sheen.",
      "Sparkle": "Adds a sunlight sheen and glinting highlight breakup similar to an icy surface sheen, but tuned for water. Higher = brighter, more natural sun-shimmer across the surface.",
      "FlowingWater": "Animate the water as a directional current instead of a mostly static surface shimmer.",
      "FollowRegionPath": "When enabled on a region-based Water effect, flow bends with the region shape and routes around curves and holes while still generally heading in the chosen direction.",
      "PathInfluence": "How strongly the flow hugs the region-derived path network instead of the raw direction. Higher = stronger path-following around curves and obstacles.",
      "Waves": "Adds broad rolling swells to the water surface instead of choppy distortion. Can be combined with Flowing Water so the swells still travel downstream.",
      "WaveStrength": "Strength and height of the rolling swell motion. Higher = fuller, more obvious wave bulges.",
      "Turbulence": "Adds wind- and storm-like chop to the water surface. Higher = rougher, noisier, more broken-up motion and reflections.",
      "FlowSpeed": "Speed of the directional water flow. Higher = faster current motion.",
      "FlowDirection": "Direction in degrees for flowing water movement.",
      "FlowStrength": "How strongly the directional current influences the water motion. Higher = more pronounced downstream flow.",
      "StillWaterSpeed": "Animation speed for calm water when Flowing Water, Waves, and Vortex Water are disabled.",
      "WaveSpeed": "Speed of the wave motion. Higher = faster rolling swells.",
      "WaveDirection": "Direction in degrees for wave travel.",
      "VortexWater": "Animate the water as a vortex centered within the region instead of directional flow.",
      "VortexSpeed": "Speed of the vortex water motion. Higher = faster swirling.",
      "VortexDirection": "Direction in degrees used to orient the vortex flow.",
      "VortexStrength": "Strength of the vortex deformation and swirl. Higher = stronger rotational pull.",
      "VortexClockwise": "Sets the vortex rotation direction. Enabled = clockwise; disabled = counterclockwise.",
      "BelowTiles": "Renders effects underneath tiles visually.",
      "DarknessActivationRange": "Only render this effect when the current scene darkness level falls within the selected range.",
      "BelowForeground": "Renders effects underneath the active foreground image visually.",
      "DarknessActivationMin": "Minimum scene darkness level required for this effect to render.",
      "DarknessActivationMax": "Maximum scene darkness level allowed for this effect to render.",
      "BlendMode": "How the adjusted color result blends with the sampled scene color.",
      "Levels": "Limit this scene effect to the selected scene levels. Leave it on All Levels to render everywhere.",
      "DarknessActivationEnabled": "Enable scene darkness gating for this effect. When disabled, the effect renders at all darkness levels."
    },
    "Particles": {
      "Groups": {
        "Other": "Other",
        "Animals": "Animals",
        "Weather": "Weather",
        "Ambient": "Ambient"
      },
      "Effects": {
        "Bats": "Bats",
        "Birds": "Birds",
        "Bubbles": "Bubbles",
        "Clouds": "Clouds",
        "Crows": "Crows",
        "Eagles": "Eagles",
        "Embers": "Embers",
        "Fog": "Fog",
        "Hail": "Hail",
        "AutumnLeaves": "Autumn Leaves",
        "Rain": "Rain",
        "Rats": "Rats",
        "Snow": "Snow",
        "Snowstorm": "Snowstorm",
        "Spiders": "Spiders",
        "Stars": "Stars",
        "SakuraBlossoms": "Sakura Blossoms",
        "SakuraBloom": "Sakura Bloom",
        "Fireflies": "Fireflies",
        "MagicCrystals": "Magic Crystals",
        "Ghosts": "Ghosts",
        "Sandstorm": "Sandstorm",
        "Fish": "Fish",
        "BatsWeatherEffectsConfig": "Bats (FXMaster)",
        "BirdsWeatherEffectsConfig": "Birds (FXMaster)",
        "BubblesWeatherEffectsConfig": "Bubbles (FXMaster)",
        "CloudsWeatherEffectsConfig": "Clouds (FXMaster)",
        "CrowsWeatherEffectsConfig": "Crows (FXMaster)",
        "EaglesWeatherEffectsConfig": "Eagles (FXMaster)",
        "EmbersWeatherEffectsConfig": "Embers (FXMaster)",
        "FogWeatherEffectsConfig": "Fog (FXMaster)",
        "HailWeatherEffectsConfig": "Hail (FXMaster)",
        "AutumnLeavesWeatherEffectsConfig": "Autumn Leaves (FXMaster)",
        "RainWeatherEffectsConfig": "Rain (FXMaster)",
        "RatsWeatherEffectsConfig": "Rats (FXMaster)",
        "SnowWeatherEffectsConfig": "Snow (FXMaster)",
        "SnowstormWeatherEffectsConfig": "Snowstorm (FXMaster)",
        "SpidersWeatherEffectsConfig": "Spiders (FXMaster)",
        "StarsWeatherEffectsConfig": "Stars (FXMaster)",
        "SakuraBlossomsWeatherEffectsConfig": "Sakura Blossoms (FXMaster)",
        "SakuraBloomWeatherEffectsConfig": "Sakura Bloom (FXMaster)",
        "FirefliesWeatherEffectsConfig": "Fireflies (FXMaster)",
        "MagicCrystalsWeatherEffectsConfig": "Magic Crystals (FXMaster)",
        "GhostsWeatherEffectsConfig": "Ghosts (FXMaster)",
        "SandstormWeatherEffectsConfig": "Sandstorm (FXMaster)",
        "FishWeatherEffectsConfig": "Fish (FXMaster)"
      },
      "BirdsAnimations": {
        "Glide": "Glide",
        "Flap": "Flap",
        "Mixed": "Mixed"
      },
      "TypeErrors": {
        "TypeUnknown": "Particle effect '{id}' is of unknown type '{type}', skipping it.",
        "TypeNotFound": "No particle effect found for type: {type}"
      },
      "CustomParticles": {
        "ManagementHeader": "{name}'s Particle Effects",
        "NoCustomParticleEffects": "No custom particle effects have been created yet.",
        "AddEffect": "Add Effect",
        "ParticleNamePlaceholder": "My Custom Particle Name",
        "BaseEffect": "Base Effect",
        "Group": "Group",
        "Textures": "Textures",
        "TexturePathsPlaceholder": "Image paths separated by commmas, Filepicker sequential select supported. Recommended to keep texture sizes as low as possible for performance, 50kb or less preferred.",
        "Icon": "Icon",
        "IconPath": "Icon Path",
        "Name": "Custom Particle Name",
        "Save": "Save",
        "Cancel": "Cancel",
        "Edit": "Edit",
        "Delete": "Delete",
        "ControlTitle": "Manage User Particle Effects",
        "ManagementTitle": "User Particle Effects",
        "ConfigTitle": "Custom Particle Effect",
        "AmbientFloat": "Ambient Float",
        "DirectionalDrift": "Directional Drift",
        "RefreshBrowserTitle": "Refresh Browser",
        "RefreshBrowserContentNew": "Would you like to refresh your browser now? The {name} effect will not be available within the Region Particle Effects menu until a refresh occurs.",
        "RefreshBrowserContentUpdated": "Would you like to refresh your browser now? The {name} effect will not be updated within the Region Particle Effects menu until a refresh occurs. Issues may occur if the effect was modified to use different base effect types or texture paths.",
        "Tooltips": {
          "Name": "Name shown in the FXMaster particle list.",
          "BaseEffect": "Choose the motion style. Directional Drift moves particles in a primary direction. Ambient Float spawns particles randomly and lets them drift on-screen.",
          "Group": "Which FXMaster category this effect appears under (Weather, Ambient, or Animals).",
          "Textures": "One or more image paths, separated by commas. Multiple images will be chosen at random per particle.",
          "Icon": "Icon image shown in the particle list."
        },
        "Errors": {
          "NameRequired": "Name is required.",
          "TexturesRequired": "You must choose at least one image for the particle texture.",
          "IconRequired": "You must choose an icon image for the custom effect.",
          "InvalidTexture": "Texture is not a supported image file: {path}",
          "InvalidIcon": "Icon is not a supported image file: {path}"
        }
      }
    },
    "Filters": {
      "Effects": {
        "Bloom": "Bloom",
        "Color": "Color",
        "Fog": "Fog",
        "Lightning": "Lightning",
        "OldFilm": "Old Film",
        "Predator": "Predator",
        "Underwater": "Underwater",
        "Water": "Water",
        "Sunlight": "Sunlight",
        "Duststorm": "Duststorm",
        "Ice": "Ice",
        "Glitch": "Glitch",
        "LightningBolts": "Lightning Bolts"
      },
      "TypeErrors": {
        "TypeUnknown": "Filter effect '{id}' is of unknown type '{type}', skipping it.",
        "TypeNotFound": "No filter effect found for type: {type}"
      }
    },
    "Regions": {
      "BehaviorNames": {
        "ParticleEffectRegionBehaviorName": "FXMaster: Particle Effects",
        "FilterEffectRegionBehaviorName": "FXMaster: Filter Effects",
        "SuppressSceneFiltersRegionBehaviorName": "FXMaster: Suppress Scene Filters",
        "SuppressSceneParticlesRegionBehaviorName": "FXMaster: Suppress Scene Particles"
      },
      "ElevationVisibility": {
        "Label": "Elevation Constraints",
        "None": "None",
        "POV": "Tokens POV",
        "Targets": "Specific Tokens POV",
        "TokenTargets": "Token UUID",
        "AlwaysVisibleForGM": "Always Visible for GM"
      }
    },
    "SoundFX": {
      "ControlTitle": "Manage Sound Effects",
      "ManagerTitle": "Sound Effects Manager",
      "AddRule": "Add Sound Rule",
      "DeleteRule": "Delete Rule",
      "AddSound": "Add Sound",
      "DeleteSound": "Delete Sound",
      "Effects": "Effects",
      "Mode": "Multi-Sound Mode",
      "ModeParallel": "Parallel (all sounds play simultaneously)",
      "ModeSequential": "Sequential (one sound at a time, played in order of priority)",
      "File": "Sound File",
      "Browse": "Browse",
      "Level": "Level",
      "DragPriority": "Drag to reprioritize",
      "NoRules": "No Sound Effects rules configured.",
      "NoSounds": "No sounds in this rule.",
      "V13Only": "Sound Effects requires Foundry VTT V13+.",
      "KindParticle": "Particle",
      "KindFilter": "Filter",
      "RuleConfigTitle": "Sound Rule",
      "EditRule": "Edit Rule",
      "Save": "Save",
      "Cancel": "Cancel",
      "Sounds": "Sounds",
      "FadeTime": "Fade Time",
      "FadeTimeHint": "Fade in/out time in milliseconds.",
      "EffectsHint": "Select one effect for a single-effect sound rule, or select multiple effects to create a combo rule with higher priority.",
      "NoEffectsSelected": "No effects selected.",
      "PausePlaylists": "Pause Playlists",
      "PausePlaylistsHint": "When this rule is active in Scene or Viewer scope, pause any currently playing playlist tracks on this client. Playback resumes when no matching rules with this option remain active.",
      "RegionSoundOptions": "Region Sound Options",
      "RegionRadius": "Region Radius",
      "RegionRadiusHintPct": "Region Radius is expressed as a percentage of each disconnected Regions component size (0-500%).",
      "RegionBoundsOnly": "Play within Region bounds",
      "RegionEasing": "Use easing",
      "RegionWalls": "Constrained by walls",
      "RegionWallsHint": "When enabled, wall and surface occlusion block sound.",
      "RegionMuffled": "Muffled by walls",
      "RegionMuffledHint": "When enabled, wall and surface occlusion muffle sound.",
      "MuffledEffect": "Muffled Effect",
      "MuffledEffectHint": "Audio effect used when a wall or surface occludes the sound.",
      "MuffledIntensity": "Muffled Effect Intensity",
      "MuffledIntensityHint": "How strongly the muffled effect is applied, from 1 to 10.",
      "MuffledEffectChoice": {
        "lowpass": "Lowpass Filter",
        "highpass": "Highpass Filter",
        "reverb": "Reverb"
      },
      "UnitMs": "ms",
      "UnitPercent": "%",
      "ConfigDescription": {
        "SceneWide": "Plays scene-wide while the selected effects are active.",
        "PointSource": "Each disconnected Region shape emits from its center with a radius of ~{pct}% of that shape's size.",
        "RegionOnly": "Audible only while a controlled Token is inside a matching Region.",
        "RegionPadding": "Full volume inside a matching Region, then fades out up to ~{pct}% beyond the boundary.",
        "SceneLevelNote": "Scene-level effects always play scene-wide."
      },
      "ConfigMode": {
        "Scene": "Scene",
        "RegionOnly": "Region Only",
        "RegionPadding": "Region + Padding",
        "RegionPointSource": "Region Point Source"
      },
      "Scope": {
        "Scene": "Scene",
        "Region": "Region",
        "Viewer": "Viewer"
      },
      "ActiveIn": "Active in: {scopes}",
      "Priority": "Priority",
      "FilePlaceholder": "assets/sounds/...",
      "RuleName": "Rule Name",
      "RuleNamePlaceholder": "Optional name (for identification)",
      "Enabled": "Enabled",
      "Disabled": "Disabled",
      "UnnamedRule": "Unnamed Rule",
      "CurrentMode": "Current Mode: {mode}"
    },
    "Layers": {
      "Title": "Manage Layers",
      "Order": "Order",
      "Effect": "Effect",
      "Source": "Source",
      "Owner": "Owner",
      "Actions": "Actions",
      "Action": "Action",
      "MoveUp": "Move up",
      "MoveDown": "Move down",
      "ResetOrder": "Reset order",
      "Empty": "No enabled particle or filter effects were found.",
      "KindParticle": "Particle",
      "KindFilter": "Filter",
      "SourceScene": "Scene",
      "SourceApi": "API",
      "SourceApiPreset": "API - Preset",
      "SourceApiMacro": "API - Macro",
      "SourceRegion": "Region",
      "ScopeRegion": "Region",
      "Level": "Level"
    },
    "RenderOrder": {
      "BelowTiles": "Below Tiles"
    },
    "BlendModes": {
      "Normal": "Normal",
      "Multiply": "Multiply",
      "Screen": "Screen",
      "Overlay": "Overlay",
      "SoftLight": "Soft Light",
      "HardLight": "Hard Light",
      "ColorDodge": "Color Dodge",
      "ColorBurn": "Color Burn",
      "Darken": "Darken",
      "Lighten": "Lighten",
      "Difference": "Difference",
      "Exclusion": "Exclusion"
    },
    "Settings": {
      "TooltipDirection": "Tooltip Direction",
      "TooltipDirectionHint": "Choose where FXMaster parameter tooltips appear when hovering labels or controls.",
      "TooltipDirectionChoices": {
        "Top": "Top",
        "Bottom": "Bottom",
        "Left": "Left",
        "Right": "Right"
      },
      "EnableLogger": "Enable FXMaster Debugging",
      "EnableLoggerHint": "Write FXMaster debugging, warning, and error messages to the browser console.",
      "PatreonSupportHint": "If you'd like to support me, Gambit! Subscribing helps support development of this and my other free modules, and also gets you access to my premium modules Gambit's FXMaster+, Gambit's Asset Previewer, and Gambit's Image Viewer!"
    },
    "Macro": {
      "Saved": "Macro '{name}' has been saved in the macro directory.",
      "UnknownParticleType": "Encountered unknown particle effect type '{type}' during macro creation. The effect was skipped.",
      "UnknownFilterType": "Encountered unknown filter effect type '{type}' during macro creation. The effect was skipped.",
      "ParticleEffectName": "Particle Effect: {label}",
      "FilterEffectName": "Filter Effect: {label}",
      "ParticleEffectsName": "Particle Effects",
      "FilterEffectsName": "Filter Effects",
      "ParticleAndFilterEffectsName": "Particle & Filter Effects",
      "NameDialogTitle": "Save Effects as Macro",
      "NameDialogHint": "Enter the name to use for the saved macro.",
      "NameLabel": "Macro Name",
      "ActionLabel": "Macro Action",
      "ActionPlay": "Play",
      "ActionToggle": "Toggle",
      "ActionHint": "Play creates a new API-effect instance. Toggle turns the saved effect group on or off.",
      "SkipFadingLabel": "Skip Fading",
      "SkipFadingHint": "Apply and remove these API effects immediately, without fade in or fade out.",
      "Save": "Save",
      "Cancel": "Cancel"
    },
    "API": {
      "PresetNotFound": "Preset '{name}' was not found.",
      "InvalidColor": "Invalid color '{color}'. Expected a hex color like #RRGGBB.",
      "InvalidSpeedLevel": "Invalid speed level '{speed}'. Supported values: very-low, low, medium, high, very-high.",
      "InvalidDensityLevel": "Invalid density level '{density}'. Supported values: very-low, low, medium, high, very-high.",
      "PlusPresetInactive": "Preset '{name}' is an FXMaster+ preset, but FXMaster+ is not active. Some effects may not load."
    },
    "Info": {
      "ControlTitle": "FXMaster Tools Overview",
      "Title": "FXMaster Overview",
      "Heading": "What can FXMaster do?",
      "Intro": "FXMaster helps GMs add atmosphere to a Scene with animated particles, visual filters, region-based effects and effect suppression, layers, reusable macros, and more!",
      "PreviewHover": "Open example preview",
      "PreviewPlaceholder": "Add an example video or image URL in fxmaster-info.js for this preview.",
      "Sections": {
        "Particles": {
          "Title": "Particle Effects",
          "Text": "Add scene-wide ambience such as rain, snow, fog, clouds, embers, stars, birds, bats, spiders, and other weather or creature effects. Each effect comes with various parameters to customize the effect's look: density, scale, speed, tint, and more."
        },
        "Filters": {
          "Title": "Filter Effects",
          "Text": "Change the look of the Scene with visual treatments like color grading, bloom, fog, old film, underwater distortion, predator vision, or lightning. Each effect comes with a number of different parameters to customize the effect's look."
        },
        "Regions": {
          "Title": "Regions and Masking",
          "Text": "Use Region behaviors to place particles or filters only in specific areas, react to token enter or exit events, respect elevation, or suppress scene effects with softer edges. In V14, FXMaster region behaviors also support native Scene Level selections for even more flexible placement and layering options."
        },
        "PlacementLevels": {
          "Title": "Placement and Levels",
          "Text": "Placement options route Scene effects below tokens, below tiles, or below foreground coverage so particles and filters sit where you want. On Scenes using native Levels on V14, Scene-wide effects can also be limited to selected floors."
        },
        "Layers": {
          "Title": "Manage Layers",
          "Text": "Review enabled scene, region, and API-created effects in one stack, then move effects up or down to control how FXMaster effects render over one another."
        },
        "ApiEffects": {
          "Title": "Manage API Effects",
          "Text": "Inspect, edit, or remove effects that were added by macros, presets, or third-party integrations without digging through Scene flags."
        },
        "SoundEffects": {
          "Title": "Manage Sound Effects",
          "Text": "When FXMaster+ is active, create sound rules that play when matching particles or filters are activated with SoundFX on, these rules can apply to both scene-wide or region-specific effects. Regions have additional configuration flexibility including easing and wall blocking/muffling options."
        },
        "UserParticles": {
          "Title": "Manage User Particle Effects",
          "Text": "When FXMaster+ is active, define custom particle effects from your own images and icons using ambient float or directional drift motion styles."
        },
        "Macros": {
          "Title": "Save Particle and Filter Effects as Macro",
          "Text": "Save the current particle and filter setup as a reusable macro from the FXMaster controls. Helpful when quick playback or toggles are useful for recurring ambience. Macros can also stack the same effect multiple times for additional customization."
        },
        "Cleanup": {
          "Title": "Clear Scene Particle and Filter Effects",
          "Text": "The cleanup control clears all Scene-level Particle Effects and Filter Effects from the current Scene."
        },
        "Performance": {
          "Title": "Performance Tips",
          "Text": "Particle density can affect performance, especially on large Scenes. FXMaster leverages Foundry's Performance Mode setting to allow limiting density on a per-user basis: Low = 25% of current particle density, Medium = 50%, High = 75%, and Maximum = 100%."
        }
      },
      "FooterText": "For full setup notes, detailed Region behavior options, and developer API examples, read the",
      "FooterReadmeLink": "full README on GitHub",
      "Actions": {
        "OpenParticleEffects": "Open Particle Effects",
        "OpenFilterEffects": "Open Filter Effects",
        "OpenRegionControls": "Open Region Controls",
        "OpenLayers": "Open Layers Manager",
        "OpenApiEffects": "Open API Manager",
        "OpenSoundEffects": "Open Sound Effects Manager",
        "OpenUserParticleEffects": "Open User Particle Effects Manager"
      }
    }
  }
}
